{
    "name": "backend",
    "version": "1.0.0",
    "scripts": {
        "start": "nodemon --exec ts-node src/app.ts --quiet"
    },
    "keywords": [],
    "author": "",
    "license": "ISC",
    "description": "",
    "devDependencies": {
        "@types/cors": "^2.8.17",
      "@types/express": "^5.0.3",
        "@types/node": "^22.5.5",
        "nodemon": "^3.1.9",
        "ts-node": "^10.9.2"
    },
    "dependencies": {
	
        "cors": "^2.8.5",
        "dotenv": "^16.4.5",
  	  	"express": "^5.1.0",
         "joi": "^17.13.3",
        "mysql2": "^3.11.3"
    }
}